{
  "name": "Networking Toolbox",
  "logo": "QmaU7tznY63wTMNNPtCQQbPBT4PNbPYFT9iq8utHwhfF47",
  "tags": [
    "network",
    "tools",
    "self-hosted",
    "homelab",
    "docker",
    "open-source",
    "utility"
  ],
  "ports": [
    { "port": 3000, "protocol": "HTTP", "label": "Web UI" }
  ],
  "short_description": "Collection of many networking utilities - port scanner, IP info, DNS tools, and more.",
  "description": "Networking Toolbox bundles offline networking utilities such as port scanner, IP lookup, DNS checker, traceroute, ping, HTTP header viewer, and SSL certificate inspector. Useful for troubleshooting, verifying configurations, and learning network diagnostics.",
  "usecases": [
    "Check your public IP and location info.",
    "Scan ports on a server.",
    "Verify DNS records and propagation.",
    "Check SSL certificate details."
  ],
  "website": "https://networking-toolbox.as93.net",
  "dependencies": [],
  "notes": [
    "Extensive collection of networking tools",
    "All tools work offline",
    "Great for troubleshooting"
  ]
}
